animesubinfo/__init__.py
animesubinfo/api.py
animesubinfo/cache.py
animesubinfo/exceptions.py
animesubinfo/models.py
animesubinfo/parsers/__init__.py
animesubinfo/parsers/catalog_parser.py
animesubinfo/parsers/search_results_parser.py
animesubinfo/py.typed
animesubinfo/utils.py
animesubinfo-0.3.0.dist-info/WHEEL
animesubinfo-0.3.0.dist-info/METADATA
animesubinfo-0.3.0.dist-info/RECORD
