Metadata-Version: 2.3
Name: animesubinfo
Version: 0.3.0
Summary: Python client for searching and downloading anime subtitles from AnimeSub.info
Author: Adrian Lehmann
Author-email: Adrian Lehmann <ownadi@gmail.com>
Requires-Dist: anitopy>=2.1.1
Requires-Dist: httpx>=0.28.1
Requires-Dist: roman>=4.2
Requires-Python: >=3.13
